tuyactl/__main__.py
tuyactl/cli.py
tuyad/__main__.py
tuyactl-0.0.1.dist-info/METADATA
tuyactl-0.0.1.dist-info/WHEEL
tuyactl-0.0.1.dist-info/entry_points.txt
tuyactl-0.0.1.dist-info/licenses/LICENSE.md
tuyactl-0.0.1.dist-info/RECORD
