Metadata-Version: 2.4
Name: tuyactl
Version: 0.0.1
Summary: A server and client cli tool for controlling Tuya devices
Author-email: "@cabra.lat" <admin@cabra.lat>
License-File: LICENSE.md
Requires-Python: >=3.13
Requires-Dist: colour>=0.1.5
Requires-Dist: numpy>=2.2.2
Requires-Dist: quart>=0.20.0
Requires-Dist: scipy>=1.15.1
Requires-Dist: tinytuya>=1.16.1
